{
    "nodeTemplete": {
        "eventPropagationSpeed": 0.0,
        "bitRate": 0,
        "speed": [
            1.0,
            1.0
        ],
        "location": [
            0.0,
            0.0
        ],
        "energy": 0.0,
        "power": 0.0,
        "snr": 0.0,
        "coverageArea": 0.0,
        "statistic": {
            "throughput": 0,
            "averageDelay": 0,
            "sendEventNums": 0,
            "reciveEventNums": 0
        }
    },
    "nodeMsgTemplete": {
        "eventPropagationSpeed": 0.0,
        "bitRate": 0,
        "speed": [
            1.0,
            1.0
        ],
        "location": [
            0.0,
            0.0
        ],
        "energy": 0.0,
        "power": 0.0,
        "snr": 0.0,
        "coverageArea": 0.0
    }
}